pyastar2d/__init__.py
pyastar2d/astar.cp38-win_amd64.pyd
pyastar2d/astar_wrapper.py
pyastar2d-1.0.6.dist-info/LICENSE
pyastar2d-1.0.6.dist-info/METADATA
pyastar2d-1.0.6.dist-info/WHEEL
pyastar2d-1.0.6.dist-info/top_level.txt
pyastar2d-1.0.6.dist-info/RECORD
