Metadata-Version: 2.1
Name: pyastar2d
Version: 1.0.6
Summary: A simple implementation of the A* algorithm for path-finding on a two-dimensional grid.
Home-page: https://github.com/hjweide/pyastar2d
Author: Hendrik Weideman
Author-email: hjweide@gmail.com
License: UNKNOWN
Platform: UNKNOWN
Classifier: Programming Language :: Python :: 3
Classifier: License :: OSI Approved :: MIT License
Classifier: Operating System :: OS Independent
Requires-Python: >=3.7
Requires-Dist: imageio
Requires-Dist: numpy
